{
  "name": "Mouride",
  "fields": [
    {
      "fieldName": "prenom",
      "fieldType": "String",
      "fieldValidateRules": ["required"]
    },
    {
      "fieldName": "nom",
      "fieldType": "String",
      "fieldValidateRules": ["required"]
    },
    {
      "fieldName": "email",
      "fieldType": "String"
    },
    {
      "fieldName": "telephone",
      "fieldType": "String",
      "fieldValidateRules": ["required"]
    },
    {
      "fieldName": "matricule",
      "fieldType": "String",
      "fieldValidateRules": ["unique"]
    }
  ],
  "relationships": [
    {
      "relationshipType": "many-to-one",
      "otherEntityName": "cuisine",
      "otherEntityRelationshipName": "mourides",
      "relationshipName": "cuisine"
    }
  ],
  "entityTableName": "mouride",
  "dto": "no",
  "pagination": "pagination",
  "service": "no",
  "jpaMetamodelFiltering": false,
  "fluentMethods": true,
  "readOnly": false,
  "embedded": false,
  "applications": "*",
  "changelogDate": "20210803204824"
}
